{
  "schema_version": "nightly_audit_v1",
  "date": "2025-12-14",
  "trace_files": [
    "C:\\Users\\kouic\\AppData\\Local\\Temp\\pytest-of-kouic\\pytest-166\\test_day_key_consistency_acros0\\trace_dump\\2025-12-14\\hub-43804.jsonl"
  ],
  "invariants": {
    "summary": {},
    "fatal_failures": 0,
    "warn_fail_rate": null
  },
  "boundary": {
    "threshold": 0.7,
    "span_count": 0,
    "max_length": 0,
    "span_chain_max": 0,
    "spans": []
  },
  "prospection": {
    "total": 1,
    "reject": 1,
    "reject_rate": 1.0,
    "accept_rate": 0.0,
    "top_jerk": [
      {
        "turn_id": "session-demo-turn-0005",
        "scenario_id": "session-demo",
        "timestamp_ms": 1765702800000,
        "jerk": 0.0,
        "temperature": 0.9,
        "accepted": false,
        "trace_file": "C:\\Users\\kouic\\AppData\\Local\\Temp\\pytest-of-kouic\\pytest-166\\test_day_key_consistency_acros0\\trace_dump\\2025-12-14\\hub-43804.jsonl"
      }
    ],
    "top_temperature": [
      {
        "turn_id": "session-demo-turn-0005",
        "scenario_id": "session-demo",
        "timestamp_ms": 1765702800000,
        "jerk": 0.0,
        "temperature": 0.9,
        "accepted": false,
        "trace_file": "C:\\Users\\kouic\\AppData\\Local\\Temp\\pytest-of-kouic\\pytest-166\\test_day_key_consistency_acros0\\trace_dump\\2025-12-14\\hub-43804.jsonl"
      }
    ]
  },
  "policy": {
    "offer_throttle_counts": {
      "cultural_pressure": 1,
      "directiveness_cap": 1
    },
    "offer_throttle_examples": {
      "cultural_pressure": [
        {
          "turn_id": "session-demo-turn-0005",
          "scenario_id": "session-demo",
          "timestamp_ms": 1765702800000,
          "trace_file": "C:\\Users\\kouic\\AppData\\Local\\Temp\\pytest-of-kouic\\pytest-166\\test_day_key_consistency_acros0\\trace_dump\\2025-12-14\\hub-43804.jsonl"
        }
      ],
      "directiveness_cap": [
        {
          "turn_id": "session-demo-turn-0005",
          "scenario_id": "session-demo",
          "timestamp_ms": 1765702800000,
          "trace_file": "C:\\Users\\kouic\\AppData\\Local\\Temp\\pytest-of-kouic\\pytest-166\\test_day_key_consistency_acros0\\trace_dump\\2025-12-14\\hub-43804.jsonl"
        }
      ]
    }
  },
  "evidence": {
    "invariants": {
      "fatal_failures": [],
      "warn_failures": []
    },
    "boundary_spans": [],
    "prospection": {
      "top_jerk": [
        {
          "turn_id": "session-demo-turn-0005",
          "scenario_id": "session-demo",
          "timestamp_ms": 1765702800000,
          "jerk": 0.0,
          "temperature": 0.9,
          "accepted": false,
          "trace_file": "C:\\Users\\kouic\\AppData\\Local\\Temp\\pytest-of-kouic\\pytest-166\\test_day_key_consistency_acros0\\trace_dump\\2025-12-14\\hub-43804.jsonl"
        }
      ],
      "top_temperature": [
        {
          "turn_id": "session-demo-turn-0005",
          "scenario_id": "session-demo",
          "timestamp_ms": 1765702800000,
          "jerk": 0.0,
          "temperature": 0.9,
          "accepted": false,
          "trace_file": "C:\\Users\\kouic\\AppData\\Local\\Temp\\pytest-of-kouic\\pytest-166\\test_day_key_consistency_acros0\\trace_dump\\2025-12-14\\hub-43804.jsonl"
        }
      ]
    },
    "policy": {
      "throttle_examples": {
        "cultural_pressure": [
          {
            "turn_id": "session-demo-turn-0005",
            "scenario_id": "session-demo",
            "timestamp_ms": 1765702800000,
            "trace_file": "C:\\Users\\kouic\\AppData\\Local\\Temp\\pytest-of-kouic\\pytest-166\\test_day_key_consistency_acros0\\trace_dump\\2025-12-14\\hub-43804.jsonl"
          }
        ],
        "directiveness_cap": [
          {
            "turn_id": "session-demo-turn-0005",
            "scenario_id": "session-demo",
            "timestamp_ms": 1765702800000,
            "trace_file": "C:\\Users\\kouic\\AppData\\Local\\Temp\\pytest-of-kouic\\pytest-166\\test_day_key_consistency_acros0\\trace_dump\\2025-12-14\\hub-43804.jsonl"
          }
        ]
      }
    }
  },
  "health": {
    "status": "YELLOW",
    "reasons": [
      {
        "level": "YELLOW",
        "reason": "prospection reject rate 1.00 outside [0.20, 0.80]"
      }
    ]
  },
  "closed_loop_trace": {
    "closed_loop_trace_ok": true,
    "missing_keys": [],
    "life_indicator_count": 1,
    "policy_prior_count": 1,
    "output_control_count": 2,
    "linked_count": 1,
    "first_seen_ts": 1765670400000,
    "last_seen_ts": 1765702800000
  },
  "recall_cue_budget": {
    "recall_cue_ok": true,
    "rarity_budget_ok": true,
    "missing_keys": [],
    "counts": {
      "memory_reference_total": 0,
      "cue_v1_count": 0,
      "suppressed_count": 0
    },
    "reasons": {}
  },
  "repair_coverage": {
    "repair_events_total": 2,
    "trigger_count": 0,
    "state_counts": {
      "RECOGNIZE": 2
    },
    "progressed_count": 0,
    "next_step_count": 0,
    "stuck_suspected": false,
    "missing_keys": []
  },
  "ru_v0_summary": {
    "gate_action_counts": {},
    "policy_version_counts": {},
    "missing_required_fields_events": 0,
    "ru_v0_events": 0
  },
  "qualia_gate_stats": {
    "memory_hint": {
      "memory_hint_rate": 0.0,
      "memory_hint_blocked_rate": 0.0,
      "memory_hint_total": 0,
      "memory_hint_shown": 0,
      "memory_hint_blocked": 0,
      "memory_hint_verbatim_block_count": 0,
      "memory_hint_key_topk": [],
      "memory_hint_category_topk": [],
      "memory_hint_category_blocked_reason": {},
      "memory_hint_blocked_reason_topk": [],
      "avg_interrupt_cost_when_blocked": 0.0,
      "community_turn_violation_count": 0,
      "memory_hint_pressure_mean": 0.0,
      "memory_hint_pressure_p95": 0.0,
      "memory_hint_pressure_delta_mean": 0.0,
      "memory_hint_blocked_pressure_mean": 0.0
    }
  }
}